permem/__init__.py
permem/client.py
permem/py.typed
permem/types.py
permem-0.1.0.dist-info/METADATA
permem-0.1.0.dist-info/WHEEL
permem-0.1.0.dist-info/licenses/LICENSE
permem-0.1.0.dist-info/RECORD
