Metadata-Version: 2.4
Name: permem
Version: 0.1.0
Summary: Persistent memory for AI - add memory to any LLM in one line
Project-URL: Homepage, https://permem.dev
Project-URL: Documentation, https://permem.dev/docs
Project-URL: Repository, https://github.com/ashish141199/permem.git
Author: Ashish Kulkarni
License-Expression: MIT
License-File: LICENSE
Keywords: ai,anthropic,embeddings,llm,memory,openai,rag,vector
Classifier: Development Status :: 3 - Alpha
Classifier: Intended Audience :: Developers
Classifier: License :: OSI Approved :: MIT License
Classifier: Programming Language :: Python :: 3
Classifier: Programming Language :: Python :: 3.9
Classifier: Programming Language :: Python :: 3.10
Classifier: Programming Language :: Python :: 3.11
Classifier: Programming Language :: Python :: 3.12
Requires-Python: >=3.9
Requires-Dist: httpx>=0.24.0
Provides-Extra: dev
Requires-Dist: pytest-asyncio>=0.21.0; extra == 'dev'
Requires-Dist: pytest>=7.0.0; extra == 'dev'
